ipsw_me/__init__.py
ipsw_me/api.py
ipsw_me/models.py
ipsw_me-1.0.0.dist-info/LICENSE
ipsw_me-1.0.0.dist-info/METADATA
ipsw_me-1.0.0.dist-info/WHEEL
ipsw_me-1.0.0.dist-info/top_level.txt
ipsw_me-1.0.0.dist-info/RECORD
