Metadata-Version: 2.1
Name: ipsw-me
Version: 1.0.0
Summary: Simple & lightweight IPSW.me API wrapper written in Python
Home-page: https://github.com/Vislate/ipsw-me-python
Author: Vislate
License: MIT
Platform: UNKNOWN
Requires-Python: >=3
Requires-Dist: requests
